azure/mgmt/azurelargeinstance/__init__.py
azure/mgmt/azurelargeinstance/_configuration.py
azure/mgmt/azurelargeinstance/_large_instance_mgmt_client.py
azure/mgmt/azurelargeinstance/_patch.py
azure/mgmt/azurelargeinstance/_serialization.py
azure/mgmt/azurelargeinstance/_vendor.py
azure/mgmt/azurelargeinstance/_version.py
azure/mgmt/azurelargeinstance/py.typed
azure/mgmt/azurelargeinstance/aio/__init__.py
azure/mgmt/azurelargeinstance/aio/_configuration.py
azure/mgmt/azurelargeinstance/aio/_large_instance_mgmt_client.py
azure/mgmt/azurelargeinstance/aio/_patch.py
azure/mgmt/azurelargeinstance/aio/operations/__init__.py
azure/mgmt/azurelargeinstance/aio/operations/_azure_large_instance_operations.py
azure/mgmt/azurelargeinstance/aio/operations/_azure_large_storage_instance_operations.py
azure/mgmt/azurelargeinstance/aio/operations/_operations.py
azure/mgmt/azurelargeinstance/aio/operations/_patch.py
azure/mgmt/azurelargeinstance/models/__init__.py
azure/mgmt/azurelargeinstance/models/_large_instance_mgmt_client_enums.py
azure/mgmt/azurelargeinstance/models/_models_py3.py
azure/mgmt/azurelargeinstance/models/_patch.py
azure/mgmt/azurelargeinstance/operations/__init__.py
azure/mgmt/azurelargeinstance/operations/_azure_large_instance_operations.py
azure/mgmt/azurelargeinstance/operations/_azure_large_storage_instance_operations.py
azure/mgmt/azurelargeinstance/operations/_operations.py
azure/mgmt/azurelargeinstance/operations/_patch.py
azure_mgmt_azurelargeinstance-1.0.0b2.dist-info/LICENSE
azure_mgmt_azurelargeinstance-1.0.0b2.dist-info/METADATA
azure_mgmt_azurelargeinstance-1.0.0b2.dist-info/WHEEL
azure_mgmt_azurelargeinstance-1.0.0b2.dist-info/top_level.txt
azure_mgmt_azurelargeinstance-1.0.0b2.dist-info/RECORD
